{
	"status":"success",
	"session":{
		"id":685,
		"created":1420646652000,
		"deleted":"n",
		"user":{
			"id":26
		},
		"expires":1423238652000,
		"token":"d22ae56a-9686-11e4-b90b-f34b9c2e13d3"
	},
	"items":[
		{
			"id":480512,
			"created":1420627827000,
			"deleted":"n",
			"externalId":"jp.co.dai-ichi-life.medical",
			"internalId":"904854306",
			"name":"健康電話相談",
			"creatorName":"Dai-ichi Life Insurance Company,Limited",
			"price":0.0,
			"source":"ios",
			"type":"Application",
			"added":1420624903000,
			"country":"jp",
			"currency":"JPY",
			"smallImage":"http://a1307.phobos.apple.com/us/r30/Purple3/v4/36/4f/5a/364f5a99-cbe1-76ff-380e-fcdae35172d6/pr_source.53x53-50.png?downloadKey=1420635703_7f043bd6c1224d2d26bdcf1c9631eabc",
			"mediumImage":"http://a175.phobos.apple.com/us/r30/Purple3/v4/36/4f/5a/364f5a99-cbe1-76ff-380e-fcdae35172d6/pr_source.75x75-65.png?downloadKey=1420635703_17516c64602775d2a74d5de8f26c77d8",
			"largeImage":"http://a988.phobos.apple.com/us/r30/Purple3/v4/36/4f/5a/364f5a99-cbe1-76ff-380e-fcdae35172d6/pr_source.100x100-75.png?downloadKey=1420635703_934a5c39e2668f8a36f56779b1f63f9f",
			"properties":"{\"usesIap\":false,\"usesIap.on\":1412629549}"
		},
		{
			"id":480510,
			"created":1420627827000,
			"deleted":"n",
			"externalId":"com.wics.WICS-WXHD",
			"internalId":"828540393",
			"name":"WICS WX for iPad",
			"creatorName":"Sinclair Broadcast Group, Inc",
			"price":0.0,
			"source":"ios",
			"type":"Application",
			"added":1420624903000,
			"country":"us",
			"currency":"USD",
			"smallImage":"http://a384.phobos.apple.com/us/r30/Purple5/v4/51/e3/f5/51e3f5e4-7f50-12eb-39d4-e76eb6e297af/mzl.mtlqbrob.53x53-50.png",
			"mediumImage":"http://a1252.phobos.apple.com/us/r30/Purple5/v4/51/e3/f5/51e3f5e4-7f50-12eb-39d4-e76eb6e297af/mzl.mtlqbrob.75x75-65.png",
			"largeImage":"http://a1777.phobos.apple.com/us/r30/Purple5/v4/51/e3/f5/51e3f5e4-7f50-12eb-39d4-e76eb6e297af/mzl.mtlqbrob.100x100-75.png",
			"properties":"{\"usesIap\":false,\"usesIap.on\":1414617984}"
		},
		{
			"id":480509,
			"created":1420627815000,
			"deleted":"n",
			"externalId":"com.spiceworks.mobilehd",
			"internalId":"544713217",
			"name":"Spiceworks HD",
			"creatorName":"Spiceworks, Inc.",
			"price":0.0,
			"source":"ios",
			"type":"Application",
			"added":1420624903000,
			"country":"gb",
			"currency":"GBP",
			"smallImage":"http://a1737.phobos.apple.com/us/r30/Purple4/v4/5e/20/83/5e208347-feed-cd26-5bde-6b019b1dbd24/mzl.qfxpyfrf.53x53-50.png",
			"mediumImage":"http://a253.phobos.apple.com/us/r30/Purple4/v4/5e/20/83/5e208347-feed-cd26-5bde-6b019b1dbd24/mzl.qfxpyfrf.75x75-65.png",
			"largeImage":"http://a890.phobos.apple.com/us/r30/Purple4/v4/5e/20/83/5e208347-feed-cd26-5bde-6b019b1dbd24/mzl.qfxpyfrf.100x100-75.png",
			"properties":"{\"usesIap\":false,\"usesIap.on\":1417560813}"
		},
		{
			"id":480508,
			"created":1420627815000,
			"deleted":"n",
			"externalId":"com.astralpad.AstralPadApp",
			"internalId":"571462034",
			"name":"AstralPad Office Collaboration – Screen sharing, video calling and documents, spreadsheet, presentation Editing",
			"creatorName":"AstralPad",
			"price":0.0,
			"source":"ios",
			"type":"Application",
			"added":1420624903000,
			"country":"gb",
			"currency":"GBP",
			"smallImage":"http://a1403.phobos.apple.com/us/r30/Purple6/v4/0e/6f/2c/0e6f2ccb-36f7-b614-620a-2f514fd08bf5/mzl.gotvacrg.53x53-50.png",
			"mediumImage":"http://a1919.phobos.apple.com/us/r30/Purple6/v4/0e/6f/2c/0e6f2ccb-36f7-b614-620a-2f514fd08bf5/mzl.gotvacrg.75x75-65.png",
			"largeImage":"http://a140.phobos.apple.com/us/r30/Purple6/v4/0e/6f/2c/0e6f2ccb-36f7-b614-620a-2f514fd08bf5/mzl.gotvacrg.100x100-75.png",
			"properties":"{\"usesIap\":false,\"usesIap.on\":1417471893}"
		},
		{
			"id":480507,
			"created":1420627815000,
			"deleted":"n",
			"externalId":"com.scania.legend2013",
			"internalId":"803899130",
			"name":"Scania Legend",
			"creatorName":"Scania Group",
			"price":0.0,
			"source":"ios",
			"type":"Application",
			"added":1420624903000,
			"country":"gb",
			"currency":"GBP",
			"smallImage":"http://a157.phobos.apple.com/us/r30/Purple3/v4/06/cf/6d/06cf6ddb-4009-b091-8cfc-7849f3086836/pr_source.53x53-50.png?downloadKey=1420635701_8a1b32168cea479c0a174bf2621d14fc",
			"mediumImage":"http://a1025.phobos.apple.com/us/r30/Purple3/v4/06/cf/6d/06cf6ddb-4009-b091-8cfc-7849f3086836/pr_source.75x75-65.png?downloadKey=1420635701_aa90ae685c4e402bf72d26fe19820f7e",
			"largeImage":"http://a414.phobos.apple.com/us/r30/Purple3/v4/06/cf/6d/06cf6ddb-4009-b091-8cfc-7849f3086836/pr_source.100x100-75.png?downloadKey=1420635701_5c596d1dce752d8e03e511a41eae5c66",
			"properties":"null"
		},
		{
			"id":480505,
			"created":1420627815000,
			"deleted":"n",
			"externalId":"com.showpad.Showpad",
			"internalId":"432293783",
			"name":"Showpad - Sales Acceleration",
			"creatorName":"Showpad",
			"price":0.0,
			"source":"ios",
			"type":"Application",
			"added":1420624903000,
			"country":"gb",
			"currency":"GBP",
			"smallImage":"http://a20.phobos.apple.com/us/r30/Purple3/v4/15/a8/96/15a89650-e4ac-7098-a8ab-0c178834274f/mzl.doxljzfo.53x53-50.png",
			"mediumImage":"http://a536.phobos.apple.com/us/r30/Purple3/v4/15/a8/96/15a89650-e4ac-7098-a8ab-0c178834274f/mzl.doxljzfo.75x75-65.png",
			"largeImage":"http://a1285.phobos.apple.com/us/r30/Purple3/v4/15/a8/96/15a89650-e4ac-7098-a8ab-0c178834274f/mzl.doxljzfo.100x100-75.png",
			"properties":"{\"usesIap\":false,\"usesIap.on\":1414967843}"
		},
		{
			"id":480504,
			"created":1420627815000,
			"deleted":"n",
			"externalId":"com.rst.bedbooking",
			"internalId":"826280602",
			"name":"BedBooking - calendar for managing reservations in accommodation facilities",
			"creatorName":"RST sp. z o.o. sp. k.",
			"price":0.0,
			"source":"ios",
			"type":"Application",
			"added":1420624903000,
			"country":"gb",
			"currency":"GBP",
			"smallImage":"http://a79.phobos.apple.com/us/r30/Purple3/v4/e5/48/ed/e548ed96-9e38-7c77-575f-72fe154fadf1/mzl.mnutgkup.53x53-50.png",
			"mediumImage":"http://a595.phobos.apple.com/us/r30/Purple3/v4/e5/48/ed/e548ed96-9e38-7c77-575f-72fe154fadf1/mzl.mnutgkup.75x75-65.png",
			"largeImage":"http://a1680.phobos.apple.com/us/r30/Purple3/v4/e5/48/ed/e548ed96-9e38-7c77-575f-72fe154fadf1/mzl.mnutgkup.100x100-75.png",
			"properties":"null"
		},
		{
			"id":480503,
			"created":1420627815000,
			"deleted":"n",
			"externalId":"com.ishore.kagazz",
			"internalId":"816155829",
			"name":"Kagazz",
			"creatorName":"i-Shore Consultancy Ltd.",
			"price":0.0,
			"source":"ios",
			"type":"Application",
			"added":1420624903000,
			"country":"gb",
			"currency":"GBP",
			"smallImage":"http://a666.phobos.apple.com/us/r30/Purple5/v4/cf/63/1c/cf631cc9-74e1-cca6-3020-8d98795e0c1b/pr_source.53x53-50.png?downloadKey=1420635702_d12711e9212c2cb09c3ffcf3dc2c75dc",
			"mediumImage":"http://a1182.phobos.apple.com/us/r30/Purple5/v4/cf/63/1c/cf631cc9-74e1-cca6-3020-8d98795e0c1b/pr_source.75x75-65.png?downloadKey=1420635702_98d734542f330fb8a34a6691a049bb96",
			"largeImage":"http://a1211.phobos.apple.com/us/r30/Purple5/v4/cf/63/1c/cf631cc9-74e1-cca6-3020-8d98795e0c1b/pr_source.100x100-75.png?downloadKey=1420635702_98963511cc3d32d337a6695d3a4e2043",
			"properties":"null"
		},
		{
			"id":480501,
			"created":1420627815000,
			"deleted":"n",
			"externalId":"com.bluetoad.idriver",
			"internalId":"375793705",
			"name":"Town and Country Ford",
			"creatorName":"BlueToad, Inc.",
			"price":0.0,
			"source":"ios",
			"type":"Application",
			"added":1420624903000,
			"country":"gb",
			"currency":"GBP",
			"smallImage":"http://a769.phobos.apple.com/us/r30/Purple/09/34/f7/mzl.jmdmwpar.53x53-50.png",
			"mediumImage":"http://a1637.phobos.apple.com/us/r30/Purple/09/34/f7/mzl.jmdmwpar.75x75-65.png",
			"largeImage":"http://a1250.phobos.apple.com/us/r30/Purple/09/34/f7/mzl.jmdmwpar.100x100-75.png",
			"properties":"null"
		},
		{
			"id":480500,
			"created":1420627815000,
			"deleted":"n",
			"externalId":"studentenwg",
			"internalId":"311831832",
			"name":"Wohnungssuche von Studenten-WG.de",
			"creatorName":"Sebastian Stadtlich",
			"price":0.0,
			"source":"ios",
			"type":"Application",
			"added":1420624903000,
			"country":"gb",
			"currency":"GBP",
			"smallImage":"http://a1396.phobos.apple.com/us/r30/Purple/v4/ff/fa/17/fffa17c0-2d98-3996-3dd8-7f197df07923/mzl.cjogbvsi.53x53-50.png",
			"mediumImage":"http://a1912.phobos.apple.com/us/r30/Purple/v4/ff/fa/17/fffa17c0-2d98-3996-3dd8-7f197df07923/mzl.cjogbvsi.75x75-65.png",
			"largeImage":"http://a773.phobos.apple.com/us/r30/Purple/v4/ff/fa/17/fffa17c0-2d98-3996-3dd8-7f197df07923/mzl.cjogbvsi.100x100-75.png",
			"properties":"null"
		}
	],
	"pager":{
		"start":10,
		"count":10,
		"totalCount":137796
	}
}