<!DOCTYPE ui:UiBinder SYSTEM "http://dl.google.com/gwt/DTD/xhtml.ent">
<ui:UiBinder xmlns:ui="urn:ui:com.google.gwt.uibinder" xmlns:g="urn:import:com.google.gwt.user.client.ui">

	<ui:import field="io.reflection.app.client.page.PageType.RegisterPageType" />

	<ui:style gss="true">
	
	</ui:style>
	<g:HTMLPanel>
		<g:InlineHyperlink ui:field="link">
			<span class="glyphicon glyphicon glyphicon-tag"></span>
			<span ui:field="name">Name</span>
		</g:InlineHyperlink>
		<g:Button ui:field="close" visible="false" />
	</g:HTMLPanel>
</ui:UiBinder> 